apkrepotool/__init__.py
apkrepotool/py.typed
apkrepotool-0.0.1.dist-info/LICENSE.AGPLv3
apkrepotool-0.0.1.dist-info/METADATA
apkrepotool-0.0.1.dist-info/WHEEL
apkrepotool-0.0.1.dist-info/entry_points.txt
apkrepotool-0.0.1.dist-info/top_level.txt
apkrepotool-0.0.1.dist-info/RECORD
